LICENSE
dupan/__init__.py
dupan/client.py
dupan/exception.py
dupan/fs.py
dupan/py.typed
python_dupan-0.0.2.1.dist-info/LICENSE
python_dupan-0.0.2.1.dist-info/METADATA
python_dupan-0.0.2.1.dist-info/WHEEL
python_dupan-0.0.2.1.dist-info/RECORD
