Metadata-Version: 2.1
Name: python-dupan
Version: 0.0.2.1
Summary: Python wrapper for `baidu webdisk <https://pan.baidu.com>`.
Home-page: https://github.com/ChenyangGao/web-mount-packs/tree/main/python-dupan-client
License: MIT
Keywords: nas,dupan,百度网盘
Author: ChenyangGao
Author-email: wosiwujm@gmail.com
Requires-Python: >=3.12,<4.0
Classifier: Development Status :: 4 - Beta
Classifier: Intended Audience :: Developers
Classifier: License :: OSI Approved :: MIT License
Classifier: Operating System :: OS Independent
Classifier: Programming Language :: Python
Classifier: Programming Language :: Python :: 3
Classifier: Programming Language :: Python :: 3.12
Classifier: Programming Language :: Python :: 3.13
Classifier: Programming Language :: Python :: 3 :: Only
Classifier: Topic :: Software Development
Classifier: Topic :: Software Development :: Libraries
Classifier: Topic :: Software Development :: Libraries :: Python Modules
Requires-Dist: ddddocr
Requires-Dist: ed2k (>=0.0.2.1)
Requires-Dist: glob_pattern (>=0.0.2)
Requires-Dist: http_response (>=0.0.2.2)
Requires-Dist: httpx
Requires-Dist: httpx_request (>=0.1.2)
Requires-Dist: lxml
Requires-Dist: multidict
Requires-Dist: orjson
Requires-Dist: python-cookietools (>=0.0.2.1)
Requires-Dist: python-filewrap (>=0.2.6.1)
Requires-Dist: python-hashtools (>=0.0.3.3)
Requires-Dist: python-httpfile (>=0.0.5)
Requires-Dist: python-iterutils (>=0.2.4.1)
Requires-Dist: python-property (>=0.0.3)
Requires-Dist: python-startfile (>=0.0.2)
Requires-Dist: python-texttools (>=0.0.3)
Requires-Dist: qrcode
Project-URL: Repository, https://github.com/ChenyangGao/web-mount-packs/tree/main/python-dupan-client
